NEMO_allauth/__init__.py
NEMO_allauth/adapter.py
NEMO_allauth/admin.py
NEMO_allauth/app_settings.py
NEMO_allauth/apps.py
NEMO_allauth/models.py
NEMO_allauth/urls.py
NEMO_allauth/static/NEMO_allauth/NEMO_allauth.css
NEMO_allauth/templates/logout_redirect.html
NEMO_allauth/templates/account/account_inactive.html
NEMO_allauth/templates/account/base.html
NEMO_allauth/templates/account/email_confirm.html
NEMO_allauth/templates/account/login.html
NEMO_allauth/templates/account/signup_closed.html
NEMO_allauth/templates/account/verification_sent.html
NEMO_allauth/templates/account/verified_email_required.html
NEMO_allauth/tests/__init__.py
NEMO_allauth/tests/test_adapter.py
NEMO_allauth/tests/test_settings.py
NEMO_allauth-2.0.3.dist-info/LICENSE
NEMO_allauth-2.0.3.dist-info/METADATA
NEMO_allauth-2.0.3.dist-info/WHEEL
NEMO_allauth-2.0.3.dist-info/top_level.txt
NEMO_allauth-2.0.3.dist-info/RECORD
